publish_to_zhihu/__init__.py
publish_to_zhihu/console.py
publish_to_zhihu/convert_latex.py
publish_to_zhihu/prepare_md.py
publish_to_zhihu/upload_images.py
publish_to_zhihu-0.1.4.dist-info/entry_points.txt
publish_to_zhihu-0.1.4.dist-info/LICENSE
publish_to_zhihu-0.1.4.dist-info/METADATA
publish_to_zhihu-0.1.4.dist-info/WHEEL
publish_to_zhihu-0.1.4.dist-info/RECORD
