Metadata-Version: 2.1
Name: publish-to-zhihu
Version: 0.1.4
Summary: Publish markdown to Zhihu
Home-page: https://github.com/anselmwang/publish_to_zhihu
Author: Anselm Wang
Author-email: anselmwang@gmail.com
Requires-Python: >=3.7,<4.0
Classifier: Programming Language :: Python :: 3
Classifier: Programming Language :: Python :: 3.7
Classifier: Programming Language :: Python :: 3.8
Classifier: Programming Language :: Python :: 3.9
Classifier: Programming Language :: Python :: 3.10
Classifier: Programming Language :: Python :: 3.11
Requires-Dist: azure-storage-blob (>=12.12.0,<13.0.0)
Requires-Dist: click (>=8.0.4,<9.0.0)
Project-URL: Repository, https://github.com/anselmwang/publish_to_zhihu
